autonomous_bag/__init__.py
autonomous_bag/reader.py
autonomous_bag-0.1.0.dist-info/METADATA
autonomous_bag-0.1.0.dist-info/WHEEL
autonomous_bag-0.1.0.dist-info/RECORD
