Metadata-Version: 2.3
Name: autonomous_bag
Version: 0.1.0
Summary: Add your description here
Author-email: todo <todo@todo.com>
Requires-Python: >=3.11
Requires-Dist: autonomous-proto>=0.1.1
Requires-Dist: rosbags>=0.10.6
